marshy_config_persisty/__init__.py
marshy_config_persisty/sqlalchemy_config.py
persisty/__init__.py
persisty/batch_edit.py
persisty/batch_edit_result.py
persisty/errors.py
persisty/result.py
persisty/result_set.py
persisty/store_meta.py
persisty/stored.py
persisty/attr/__init__.py
persisty/attr/attr.py
persisty/attr/attr_filter.py
persisty/attr/attr_filter_op.py
persisty/attr/attr_type.py
persisty/attr/generator/__init__.py
persisty/attr/generator/attr_value_generator_abc.py
persisty/attr/generator/default_value_generator.py
persisty/attr/generator/defaults.py
persisty/attr/generator/fixed_value_generator.py
persisty/attr/generator/int_sequence_generator.py
persisty/attr/generator/str_sequence_generator.py
persisty/attr/generator/timestamp_generator.py
persisty/attr/generator/uuid_generator.py
persisty/factory/__init__.py
persisty/factory/caching_store_factory.py
persisty/factory/store_factory.py
persisty/factory/store_factory_abc.py
persisty/finder/__init__.py
persisty/finder/module_store_meta_finder.py
persisty/finder/store_action_finder.py
persisty/finder/store_meta_finder_abc.py
persisty/impl/__init__.py
persisty/impl/dynamodb/__init__.py
persisty/impl/dynamodb/dynamodb_key_config.py
persisty/impl/dynamodb/dynamodb_store_factory.py
persisty/impl/dynamodb/dynamodb_table_store.py
persisty/impl/dynamodb/partition_sort_index.py
persisty/impl/mem/__init__.py
persisty/impl/mem/mem_store.py
persisty/impl/mem/mem_store_factory.py
persisty/impl/open_search/__init__.py
persisty/impl/open_search/open_search_doc_store.py
persisty/impl/sqlalchemy/__init__.py
persisty/impl/sqlalchemy/sqlalchemy_column_converter.py
persisty/impl/sqlalchemy/sqlalchemy_constraint_converter.py
persisty/impl/sqlalchemy/sqlalchemy_context.py
persisty/impl/sqlalchemy/sqlalchemy_context_factory.py
persisty/impl/sqlalchemy/sqlalchemy_context_factory_abc.py
persisty/impl/sqlalchemy/sqlalchemy_table_converter.py
persisty/impl/sqlalchemy/sqlalchemy_table_store.py
persisty-0.0.17.dist-info/METADATA
persisty-0.0.17.dist-info/WHEEL
persisty-0.0.17.dist-info/top_level.txt
persisty-0.0.17.dist-info/RECORD
