Metadata-Version: 2.1
Name: persisty
Version: 0.0.17
Summary: A better persistence layer for python
Home-page: https://github.com/tofarr/lambsync
Author: Tim O'Farrell
Author-email: tofarr@gmail.com
Classifier: Programming Language :: Python :: 3
Classifier: License :: OSI Approved :: MIT License
Classifier: Operating System :: OS Independent
Requires-Dist: pyaes ~=1.6
Requires-Dist: servey ~=3.0
Provides-Extra: all
Requires-Dist: pytest ~=7.2 ; extra == 'all'
Requires-Dist: pytest-xdist ~=3.2 ; extra == 'all'
Requires-Dist: opensearch-py ~=2.2 ; extra == 'all'
Requires-Dist: SQLAlchemy ~=1.4 ; extra == 'all'
Requires-Dist: pylint ~=3.0 ; extra == 'all'
Requires-Dist: pytest-cov ~=4.0 ; extra == 'all'
Requires-Dist: alembic ~=1.12 ; extra == 'all'
Requires-Dist: black ~=23.3 ; extra == 'all'
Requires-Dist: servey[scheduler] ~=3.0 ; extra == 'all'
Requires-Dist: boto3 ~=1.26 ; extra == 'all'
Requires-Dist: servey[serverless] ~=3.0 ; extra == 'all'
Requires-Dist: moto ~=3.1 ; extra == 'all'
Requires-Dist: servey[server] ~=3.0 ; extra == 'all'
Provides-Extra: dev
Requires-Dist: black ~=23.3 ; extra == 'dev'
Requires-Dist: pytest ~=7.2 ; extra == 'dev'
Requires-Dist: pytest-cov ~=4.0 ; extra == 'dev'
Requires-Dist: pytest-xdist ~=3.2 ; extra == 'dev'
Requires-Dist: pylint ~=3.0 ; extra == 'dev'
Requires-Dist: boto3 ~=1.26 ; extra == 'dev'
Requires-Dist: moto ~=3.1 ; extra == 'dev'
Provides-Extra: scheduler
Requires-Dist: servey[scheduler] ~=3.0 ; extra == 'scheduler'
Provides-Extra: server
Requires-Dist: servey[server] ~=3.0 ; extra == 'server'
Provides-Extra: serverless
Requires-Dist: servey[serverless] ~=3.0 ; extra == 'serverless'
Requires-Dist: opensearch-py ~=2.2 ; extra == 'serverless'
Provides-Extra: sql
Requires-Dist: SQLAlchemy ~=1.4 ; extra == 'sql'
Provides-Extra: sqldev
Requires-Dist: alembic ~=1.12 ; extra == 'sqldev'
